README
setup.py
VisualHash/__init__.py
VisualHashPrivate/FractalTransform.c
VisualHashPrivate/__init__.py
VisualHashPrivate/identicon.py
VisualHashPrivate/randomart.py
visual_hash.egg-info/PKG-INFO
visual_hash.egg-info/SOURCES.txt
visual_hash.egg-info/dependency_links.txt
visual_hash.egg-info/requires.txt
visual_hash.egg-info/top_level.txt