Metadata-Version: 1.1
Name: visual-hash
Version: 0.0.0.9
Summary: A package to generate visual hashes.
Home-page: https://github.com/droundy/visual-hash
Author: David Roundy
Author-email: daveroundy@gmail.com
License: BSD
Platform: UNKNOWN
Classifier: Development Status :: 3 - Alpha
Classifier: License :: OSI Approved :: BSD License
